setup.py
glyph/__init__.py
glyph/data.py
glyph/encoding.py
glyph/server.py
glyph/resource/__init__.py
glyph/resource/base.py
glyph/resource/handler.py
glyph/resource/persistent.py
glyph/resource/router.py
glyph/resource/transient.py
glyph_rpc.egg-info/PKG-INFO
glyph_rpc.egg-info/SOURCES.txt
glyph_rpc.egg-info/dependency_links.txt
glyph_rpc.egg-info/top_level.txt