Metadata-Version: 1.0
Name: glyph-rpc
Version: 0.1-20120412
Summary: glyph-rpc is yet another http rpc library, but it tries to exploit http rather than simply tunnel requests over it.
Home-page: UNKNOWN
Author: tef
Author-email: tef@twentygototen.org
License: MIT License
Platform: UNKNOWN
